{"is_source_file": true, "format": "JavaScript", "description": "A custom React hook that provides a way to manage state with local storage, allowing for persistent user data across sessions.", "external_files": ["react"], "external_methods": ["useState"], "published": ["useLocalStorage"], "classes": [], "methods": [{"name": "useLocalStorage(key, initialValue)", "description": "A hook that initializes state with a value from localStorage and provides a method to update both the state and localStorage.", "scope": "", "scopeKind": ""}], "calls": ["window.localStorage.getItem", "window.localStorage.setItem"], "search-terms": ["local storage", "persistent state", "React hook"], "state": 2, "file_id": 27, "knowledge_revision": 57, "git_revision": "5008745451aebb09a1694baf673e8d3d40a65db9", "ctags": [{"_type": "tag", "name": "useLocalStorage", "path": "/tmp/kavia/workspace/code-generation/note-manager-905-914/react_frontend/src/hooks/useLocalStorage.js", "pattern": "/^export function useLocalStorage(key, initialValue) {$/", "language": "JavaScript", "kind": "function", "signature": "(key, initialValue)"}], "hash": "1a6190b9ab87b8f798fe812e9316478b", "format-version": 4, "code-base-name": "react_frontend", "filename": "react_frontend/src/hooks/useLocalStorage.js", "revision_history": [{"57": "5008745451aebb09a1694baf673e8d3d40a65db9"}]}