{"is_source_file": true, "format": "JavaScript", "description": "Main application file for a note management React application, implementing the UI and state management for creating, updating, and deleting notes.", "external_files": ["./App.css"], "external_methods": ["React.createContext", "React.useEffect", "React.useState", "React.useContext", "React.useCallback"], "published": ["useNotes", "NotesProvider"], "classes": [], "methods": [{"name": "createEmptyNote()", "description": "Creates a new empty note object with a unique ID and default fields.", "scope": "", "scopeKind": ""}, {"name": "formatDateTime(ts)", "description": "Formats a timestamp into a readable date and time string.", "scope": "", "scopeKind": ""}, {"name": "Header()", "description": "Renders the header for the application, displaying the title 'Notes'.", "scope": "", "scopeKind": ""}, {"name": "NoteList({ search, onSetSearch })", "description": "Displays a list of notes with filtering capabilities based on user input.", "scope": "", "scopeKind": ""}, {"name": "NoteEditor()", "description": "Provides an interface for editing the contents and title of a selected note.", "scope": "", "scopeKind": ""}, {"name": "FloatingActionButton()", "description": "Renders a floating action button that allows users to create a new note.", "scope": "", "scopeKind": ""}, {"name": "Layout()", "description": "Controls the main layout of the application, aggregating the NoteList and NoteEditor components.", "scope": "", "scopeKind": ""}, {"name": "App()", "description": "Main application component that sets up the notes provider and renders the overall layout.", "scope": "", "scopeKind": ""}, {"name": "NotesProvider({ children })", "scope": "", "scopeKind": "", "description": "unavailable"}, {"name": "handler(e)", "scope": "NoteEditor", "scopeKind": "function", "description": "unavailable"}, {"name": "useNotes()", "scope": "", "scopeKind": "", "description": "unavailable"}], "calls": ["localStorage.getItem", "localStorage.setItem", "JSON.parse", "JSON.stringify", "React.createElement", "React.Component", "React.useEffect", "React.useCallback", "React.useState", "document.documentElement.style.setProperty"], "search-terms": ["note", "NotesProvider", "createNote", "updateNote", "deleteNote"], "state": 2, "file_id": 3, "knowledge_revision": 26, "git_revision": "fc6aafff506588b14dd5491371aa1370b8622c3c", "revision_history": [{"24": "fc6aafff506588b14dd5491371aa1370b8622c3c"}, {"26": "fc6aafff506588b14dd5491371aa1370b8622c3c"}], "ctags": [{"_type": "tag", "name": "120", "path": "/tmp/kavia/workspace/code-generation/note-manager-905-914/react_frontend/src/App.js", "pattern": "/^          maxLength={120}$/", "language": "JavaScript", "kind": "field", "scope": "maxLength", "scopeKind": "class"}, {"_type": "tag", "name": "7000", "path": "/tmp/kavia/workspace/code-generation/note-manager-905-914/react_frontend/src/App.js", "pattern": "/^        maxLength={7000}$/", "language": "JavaScript", "kind": "field", "scope": "maxLength", "scopeKind": "class"}, {"_type": "tag", "name": "App", "path": "/tmp/kavia/workspace/code-generation/note-manager-905-914/react_frontend/src/App.js", "pattern": "/^function App() {$/", "language": "JavaScript", "kind": "function", "signature": "()"}, {"_type": "tag", "name": "FloatingActionButton", "path": "/tmp/kavia/workspace/code-generation/note-manager-905-914/react_frontend/src/App.js", "pattern": "/^function FloatingActionButton() {$/", "language": "JavaScript", "kind": "function", "signature": "()"}, {"_type": "tag", "name": "Header", "path": "/tmp/kavia/workspace/code-generation/note-manager-905-914/react_frontend/src/App.js", "pattern": "/^function Header() {$/", "language": "JavaScript", "kind": "function", "signature": "()"}, {"_type": "tag", "name": "Layout", "path": "/tmp/kavia/workspace/code-generation/note-manager-905-914/react_frontend/src/App.js", "pattern": "/^function Layout() {$/", "language": "JavaScript", "kind": "function", "signature": "()"}, {"_type": "tag", "name": "NOTES_KEY", "path": "/tmp/kavia/workspace/code-generation/note-manager-905-914/react_frontend/src/App.js", "pattern": "/^const NOTES_KEY = \"notes\";$/", "language": "JavaScript", "kind": "constant"}, {"_type": "tag", "name": "NoteEditor", "path": "/tmp/kavia/workspace/code-generation/note-manager-905-914/react_frontend/src/App.js", "pattern": "/^function NoteEditor() {$/", "language": "JavaScript", "kind": "function", "signature": "()"}, {"_type": "tag", "name": "NoteList", "path": "/tmp/kavia/workspace/code-generation/note-manager-905-914/react_frontend/src/App.js", "pattern": "/^function NoteList({ search, onSetSearch }) {$/", "language": "JavaScript", "kind": "function", "signature": "({ search, onSetSearch })"}, {"_type": "tag", "name": "NotesContext", "path": "/tmp/kavia/workspace/code-generation/note-manager-905-914/react_frontend/src/App.js", "pattern": "/^const NotesContext = React.createContext();$/", "language": "JavaScript", "kind": "constant"}, {"_type": "tag", "name": "NotesProvider", "path": "/tmp/kavia/workspace/code-generation/note-manager-905-914/react_frontend/src/App.js", "pattern": "/^function NotesProvider({ children }) {$/", "language": "JavaScript", "kind": "function", "signature": "({ children })"}, {"_type": "tag", "name": "background", "path": "/tmp/kavia/workspace/code-generation/note-manager-905-914/react_frontend/src/App.js", "pattern": "/^  background: \"#f9fafb\",$/", "language": "JavaScript", "kind": "property", "scope": "theme", "scopeKind": "class"}, {"_type": "tag", "name": "content", "path": "/tmp/kavia/workspace/code-generation/note-manager-905-914/react_frontend/src/App.js", "pattern": "/^        value={content}$/", "language": "JavaScript", "kind": "field", "scope": "value", "scopeKind": "class"}, {"_type": "tag", "name": "createEmptyNote", "path": "/tmp/kavia/workspace/code-generation/note-manager-905-914/react_frontend/src/App.js", "pattern": "/^function createEmptyNote() {$/", "language": "JavaScript", "kind": "function", "signature": "()"}, {"_type": "tag", "name": "createNote", "path": "/tmp/kavia/workspace/code-generation/note-manager-905-914/react_frontend/src/App.js", "pattern": "/^      onClick={createNote}$/", "language": "JavaScript", "kind": "field", "scope": "FloatingActionButton.onClick", "scopeKind": "class"}, {"_type": "tag", "name": "error", "path": "/tmp/kavia/workspace/code-generation/note-manager-905-914/react_frontend/src/App.js", "pattern": "/^  error: \"#EF4444\",$/", "language": "JavaScript", "kind": "property", "scope": "theme", "scopeKind": "class"}, {"_type": "tag", "name": "false", "path": "/tmp/kavia/workspace/code-generation/note-manager-905-914/react_frontend/src/App.js", "pattern": "/^        spellCheck={false}$/", "language": "JavaScript", "kind": "field", "scope": "spellCheck", "scopeKind": "class"}, {"_type": "tag", "name": "formatDateTime", "path": "/tmp/kavia/workspace/code-generation/note-manager-905-914/react_frontend/src/App.js", "pattern": "/^function formatDateTime(ts) {$/", "language": "JavaScript", "kind": "function", "signature": "(ts)"}, {"_type": "tag", "name": "gradient", "path": "/tmp/kavia/workspace/code-generation/note-manager-905-914/react_frontend/src/App.js", "pattern": "/^  gradient:$/", "language": "JavaScript", "kind": "property", "scope": "theme", "scopeKind": "class"}, {"_type": "tag", "name": "handler", "path": "/tmp/kavia/workspace/code-generation/note-manager-905-914/react_frontend/src/App.js", "pattern": "/^    function handler(e) {$/", "language": "JavaScript", "kind": "function", "signature": "(e)", "scope": "NoteEditor", "scopeKind": "function"}, {"_type": "tag", "name": "notes", "path": "/tmp/kavia/workspace/code-generation/note-manager-905-914/react_frontend/src/App.js", "pattern": "/^    notes,$/", "language": "JavaScript", "kind": "field", "scope": "NotesProvider.value", "scopeKind": "class"}, {"_type": "tag", "name": "primary", "path": "/tmp/kavia/workspace/code-generation/note-manager-905-914/react_frontend/src/App.js", "pattern": "/^  primary: \"#2563EB\",$/", "language": "JavaScript", "kind": "property", "scope": "theme", "scopeKind": "class"}, {"_type": "tag", "name": "search", "path": "/tmp/kavia/workspace/code-generation/note-manager-905-914/react_frontend/src/App.js", "pattern": "/^        value={search}$/", "language": "JavaScript", "kind": "field", "scope": "value", "scopeKind": "class"}, {"_type": "tag", "name": "search", "path": "/tmp/kavia/workspace/code-generation/note-manager-905-914/react_frontend/src/App.js", "pattern": "/^      <NoteList search={search} onSetSearch={setSearch} \\/>$/", "language": "JavaScript", "kind": "field", "scope": "AnonymousClassea5ac6b30701", "scopeKind": "class"}, {"_type": "tag", "name": "secondary", "path": "/tmp/kavia/workspace/code-generation/note-manager-905-914/react_frontend/src/App.js", "pattern": "/^  secondary: \"#F59E0B\",$/", "language": "JavaScript", "kind": "property", "scope": "theme", "scopeKind": "class"}, {"_type": "tag", "name": "success", "path": "/tmp/kavia/workspace/code-generation/note-manager-905-914/react_frontend/src/App.js", "pattern": "/^  success: \"#F59E0B\",$/", "language": "JavaScript", "kind": "property", "scope": "theme", "scopeKind": "class"}, {"_type": "tag", "name": "surface", "path": "/tmp/kavia/workspace/code-generation/note-manager-905-914/react_frontend/src/App.js", "pattern": "/^  surface: \"#ffffff\",$/", "language": "JavaScript", "kind": "property", "scope": "theme", "scopeKind": "class"}, {"_type": "tag", "name": "text", "path": "/tmp/kavia/workspace/code-generation/note-manager-905-914/react_frontend/src/App.js", "pattern": "/^  text: \"#111827\",$/", "language": "JavaScript", "kind": "property", "scope": "theme", "scopeKind": "class"}, {"_type": "tag", "name": "theme", "path": "/tmp/kavia/workspace/code-generation/note-manager-905-914/react_frontend/src/App.js", "pattern": "/^const theme = {$/", "language": "JavaScript", "kind": "class"}, {"_type": "tag", "name": "title", "path": "/tmp/kavia/workspace/code-generation/note-manager-905-914/react_frontend/src/App.js", "pattern": "/^          value={title}$/", "language": "JavaScript", "kind": "field", "scope": "value", "scopeKind": "class"}, {"_type": "tag", "name": "true", "path": "/tmp/kavia/workspace/code-generation/note-manager-905-914/react_frontend/src/App.js", "pattern": "/^        spellCheck={true}$/", "language": "JavaScript", "kind": "field", "scope": "spellCheck", "scopeKind": "class"}, {"_type": "tag", "name": "useNotes", "path": "/tmp/kavia/workspace/code-generation/note-manager-905-914/react_frontend/src/App.js", "pattern": "/^export function useNotes() {$/", "language": "JavaScript", "kind": "function", "signature": "()"}, {"_type": "tag", "name": "value", "path": "/tmp/kavia/workspace/code-generation/note-manager-905-914/react_frontend/src/App.js", "pattern": "/^  return <NotesContext.Provider value={value}>{children}<\\/NotesContext.Provider>;$/", "language": "JavaScript", "kind": "field", "scope": "Provider", "scopeKind": "class"}], "hash": "456c7afdcbbc2be9f60bcb075f26bd05", "format-version": 4, "code-base-name": "react_frontend", "filename": "react_frontend/src/App.js", "fields": [{"name": "maxLength={120}", "scope": "maxLength", "scopeKind": "class", "description": "unavailable"}, {"name": "maxLength={7000}", "scope": "maxLength", "scopeKind": "class", "description": "unavailable"}, {"name": "background: \"#f9fafb\",", "scope": "theme", "scopeKind": "class", "description": "unavailable"}, {"name": "value={content}", "scope": "value", "scopeKind": "class", "description": "unavailable"}, {"name": "onClick={createNote}", "scope": "FloatingActionButton.onClick", "scopeKind": "class", "description": "unavailable"}, {"name": "error: \"#EF4444\",", "scope": "theme", "scopeKind": "class", "description": "unavailable"}, {"name": "spellCheck={false}", "scope": "spellCheck", "scopeKind": "class", "description": "unavailable"}, {"name": "gradient:", "scope": "theme", "scopeKind": "class", "description": "unavailable"}, {"name": "notes,", "scope": "NotesProvider.value", "scopeKind": "class", "description": "unavailable"}, {"name": "primary: \"#2563EB\",", "scope": "theme", "scopeKind": "class", "description": "unavailable"}, {"name": "value={search}", "scope": "value", "scopeKind": "class", "description": "unavailable"}, {"name": "<NoteList search={search} onSetSearch={setSearch} \\/>", "scope": "AnonymousClassea5ac6b30701", "scopeKind": "class", "description": "unavailable"}, {"name": "secondary: \"#F59E0B\",", "scope": "theme", "scopeKind": "class", "description": "unavailable"}, {"name": "success: \"#F59E0B\",", "scope": "theme", "scopeKind": "class", "description": "unavailable"}, {"name": "surface: \"#ffffff\",", "scope": "theme", "scopeKind": "class", "description": "unavailable"}, {"name": "text: \"#111827\",", "scope": "theme", "scopeKind": "class", "description": "unavailable"}, {"name": "value={title}", "scope": "value", "scopeKind": "class", "description": "unavailable"}, {"name": "spellCheck={true}", "scope": "spellCheck", "scopeKind": "class", "description": "unavailable"}, {"name": "return <NotesContext.Provider value={value}>{children}<\\/NotesContext.Provider>;", "scope": "Provider", "scopeKind": "class", "description": "unavailable"}]}